awslabs/__init__.py
awslabs/core_mcp_server/__init__.py
awslabs/core_mcp_server/server.py
awslabs/core_mcp_server/static/__init__.py
mseep_awslabs_core_mcp_server-1.0.2.dist-info/licenses/LICENSE
mseep_awslabs_core_mcp_server-1.0.2.dist-info/licenses/NOTICE
tests/__init__.py
tests/conftest.py
tests/test_init.py
tests/test_main.py
tests/test_response_types.py
tests/test_server.py
tests/test_static.py
mseep_awslabs_core_mcp_server-1.0.2.dist-info/METADATA
mseep_awslabs_core_mcp_server-1.0.2.dist-info/WHEEL
mseep_awslabs_core_mcp_server-1.0.2.dist-info/top_level.txt
mseep_awslabs_core_mcp_server-1.0.2.dist-info/RECORD
